imagetext_captions/__init__.py
imagetext_captions/imagetext_captions.py
ImageTextCaptions-0.1.0.dist-info/METADATA
ImageTextCaptions-0.1.0.dist-info/WHEEL
ImageTextCaptions-0.1.0.dist-info/top_level.txt
ImageTextCaptions-0.1.0.dist-info/RECORD
