Metadata-Version: 2.1
Name: ImageTextCaptions
Version: 0.1.0
Summary: A module to generate captions for images using Google AI's Vertex AI Platform.
Home-page: https://github.com/binxio/imagetext-captions
Author: Dennis Vink
Author-email: dennis.vink@xebia.com
Classifier: License :: OSI Approved :: MIT License
Classifier: Programming Language :: Python
Classifier: Programming Language :: Python :: 3
Classifier: Programming Language :: Python :: 3.7
Requires-Dist: requests (>=2.26.0)
Requires-Dist: google-auth (>=1.35.0)
